cucll/__init__.py
cucll/learn/__init__.py
cucll/learn/_imports.py
cucll/learn/clean_data.py
cucll/learn/explore_data.py
cucll/learn/utils.py
cucll_learn-0.2.0.dist-info/licenses/LICENSE
cucll_learn-0.2.0.dist-info/METADATA
cucll_learn-0.2.0.dist-info/WHEEL
cucll_learn-0.2.0.dist-info/top_level.txt
cucll_learn-0.2.0.dist-info/RECORD
